fcr/__init__.py
fcr/fcr.py
fcr-0.0.3.dist-info/LICENSE
fcr-0.0.3.dist-info/METADATA
fcr-0.0.3.dist-info/WHEEL
fcr-0.0.3.dist-info/top_level.txt
fcr-0.0.3.dist-info/RECORD
